{
  "fetchedAt": "2026-05-02T20:48:42.059Z",
  "data": {
    "match": {
      "id": 35140644,
      "isFinalized": true,
      "isTournament": false,
      "tableNumber": null,
      "division": {
        "id": 344194,
        "electronicScoringEnabled": true,
        "__typename": "Division",
        "scheduleInEdit": false,
        "type": "EIGHT"
      },
      "league": {
        "id": 890,
        "esEnabled": true,
        "__typename": "League",
        "name": "APA of South Jersey",
        "currentSessionId": 138,
        "isElectronicPaymentsEnabled": false,
        "country": {
          "id": 1,
          "__typename": "Country"
        }
      },
      "__typename": "Match",
      "type": "EIGHT",
      "startTime": "2022-07-14T19:30:00-04:00",
      "week": 9,
      "isBye": false,
      "isMine": false,
      "isScored": true,
      "scoresheet": null,
      "isPaid": null,
      "timeZone": {
        "id": "169",
        "name": "America/New_York",
        "__typename": "TimeZone"
      },
      "location": {
        "id": 102500,
        "phone": "+18563447298",
        "name": "South Jersey Billiards",
        "address": {
          "id": 73668,
          "name": "South Jersey Billiards",
          "address1": "600 N White Horse Pike",
          "address2": "",
          "city": "Somerdale",
          "zip": "08083",
          "latitude": 39.8514045,
          "longitude": -75.02370239999999,
          "__typename": "Address"
        },
        "__typename": "HostLocation"
      },
      "home": {
        "id": 12041902,
        "name": "Clean 'em Up",
        "number": "06109",
        "isMine": false,
        "league": {
          "id": 890,
          "slug": "southjersey",
          "__typename": "League"
        },
        "division": {
          "id": 344194,
          "type": "EIGHT",
          "__typename": "Division"
        },
        "roster": [
          {
            "id": 85062950,
            "memberNumber": "08228872",
            "displayName": "Mailman Williams",
            "matchesWon": 4,
            "matchesPlayed": 6,
            "pa": 0.5555555555555556,
            "ppm": 1.6666666666666667,
            "skillLevel": 6,
            "__typename": "EightBallPlayer",
            "member": {
              "id": 1150687,
              "__typename": "Member"
            }
          },
          {
            "id": 85062946,
            "memberNumber": "08222277",
            "displayName": "Stephen Pressey",
            "matchesWon": 6,
            "matchesPlayed": 7,
            "pa": 0.7142857142857143,
            "ppm": 2.142857142857143,
            "skillLevel": 4,
            "__typename": "EightBallPlayer",
            "member": {
              "id": 949937,
              "__typename": "Member"
            }
          },
          {
            "id": 85062949,
            "memberNumber": "08229788",
            "displayName": "Ron Dolente",
            "matchesWon": 5,
            "matchesPlayed": 7,
            "pa": 0.4761904761904762,
            "ppm": 1.4285714285714286,
            "skillLevel": 7,
            "__typename": "EightBallPlayer",
            "member": {
              "id": 1226829,
              "__typename": "Member"
            }
          },
          {
            "id": 85062952,
            "memberNumber": "08200846",
            "displayName": "Chet Reklewski",
            "matchesWon": 5,
            "matchesPlayed": 8,
            "pa": 0.5,
            "ppm": 1.5,
            "skillLevel": 5,
            "__typename": "EightBallPlayer",
            "member": {
              "id": 2595790,
              "__typename": "Member"
            }
          },
          {
            "id": 85062953,
            "memberNumber": "08209227",
            "displayName": "Tedd Teschner",
            "matchesWon": 8,
            "matchesPlayed": 10,
            "pa": 0.7999999999999999,
            "ppm": 2.4,
            "skillLevel": 3,
            "__typename": "EightBallPlayer",
            "member": {
              "id": 2946214,
              "__typename": "Member"
            }
          },
          {
            "id": 85062951,
            "memberNumber": "08240179",
            "displayName": "Lou Cirucci",
            "matchesWon": 4,
            "matchesPlayed": 8,
            "pa": 0.4166666666666667,
            "ppm": 1.25,
            "skillLevel": 4,
            "__typename": "EightBallPlayer",
            "member": {
              "id": 1423098,
              "__typename": "Member"
            }
          },
          {
            "id": 85062947,
            "memberNumber": "08222592",
            "displayName": "Steve Timm",
            "matchesWon": 2,
            "matchesPlayed": 8,
            "pa": 0.20833333333333334,
            "ppm": 0.625,
            "skillLevel": 5,
            "__typename": "EightBallPlayer",
            "member": {
              "id": 1017859,
              "__typename": "Member"
            }
          },
          {
            "id": 85319882,
            "memberNumber": "08202034",
            "displayName": "Jim Barnabei",
            "matchesWon": 5,
            "matchesPlayed": 8,
            "pa": 0.5,
            "ppm": 1.5,
            "skillLevel": 3,
            "__typename": "EightBallPlayer",
            "member": {
              "id": 2400204,
              "__typename": "Member"
            }
          }
        ],
        "__typename": "Team"
      },
      "away": {
        "id": 12060085,
        "name": "Thirsty Hound I",
        "number": "06111",
        "isMine": false,
        "league": {
          "id": 890,
          "slug": "southjersey",
          "__typename": "League"
        },
        "division": {
          "id": 344194,
          "type": "EIGHT",
          "__typename": "Division"
        },
        "roster": [
          {
            "id": 85193841,
            "memberNumber": "08208853",
            "displayName": "Krystion Geesaman",
            "matchesWon": 2,
            "matchesPlayed": 11,
            "pa": 0.393939393939394,
            "ppm": 1.1818181818181819,
            "skillLevel": 3,
            "__typename": "EightBallPlayer",
            "member": {
              "id": 2942824,
              "__typename": "Member"
            }
          },
          {
            "id": 85193842,
            "memberNumber": "08204961",
            "displayName": "JR Geesaman Jr.",
            "matchesWon": 4,
            "matchesPlayed": 10,
            "pa": 0.3333333333333333,
            "ppm": 1,
            "skillLevel": 3,
            "__typename": "EightBallPlayer",
            "member": {
              "id": 2807123,
              "__typename": "Member"
            }
          },
          {
            "id": 85193843,
            "memberNumber": "08204069",
            "displayName": "Timothy Geesaman",
            "matchesWon": 4,
            "matchesPlayed": 8,
            "pa": 0.4166666666666667,
            "ppm": 1.25,
            "skillLevel": 4,
            "__typename": "EightBallPlayer",
            "member": {
              "id": 2753287,
              "__typename": "Member"
            }
          },
          {
            "id": 85193847,
            "memberNumber": "08212769",
            "displayName": "John Herman",
            "matchesWon": 2,
            "matchesPlayed": 5,
            "pa": 0.3333333333333333,
            "ppm": 1,
            "skillLevel": 3,
            "__typename": "EightBallPlayer",
            "member": {
              "id": 3169797,
              "__typename": "Member"
            }
          },
          {
            "id": 85193849,
            "memberNumber": "08215371",
            "displayName": "John Free-26 Makin",
            "matchesWon": 2,
            "matchesPlayed": 4,
            "pa": 0.3333333333333333,
            "ppm": 1,
            "skillLevel": 5,
            "__typename": "EightBallPlayer",
            "member": {
              "id": 737608,
              "__typename": "Member"
            }
          },
          {
            "id": 85193850,
            "memberNumber": "08207118",
            "displayName": "Larry Bythrow",
            "matchesWon": 4,
            "matchesPlayed": 10,
            "pa": 0.39999999999999997,
            "ppm": 1.2,
            "skillLevel": 2,
            "__typename": "EightBallPlayer",
            "member": {
              "id": 3220246,
              "__typename": "Member"
            }
          },
          {
            "id": 85259796,
            "memberNumber": "08204649",
            "displayName": "Dillon Mills",
            "matchesWon": 1,
            "matchesPlayed": 9,
            "pa": 0.1111111111111111,
            "ppm": 0.3333333333333333,
            "skillLevel": 2,
            "__typename": "EightBallPlayer",
            "member": {
              "id": 3235499,
              "__typename": "Member"
            }
          },
          {
            "id": 85259797,
            "memberNumber": "08215468",
            "displayName": "Patrick Daley",
            "matchesWon": 2,
            "matchesPlayed": 3,
            "pa": 0.4444444444444444,
            "ppm": 1.3333333333333333,
            "skillLevel": 7,
            "__typename": "EightBallPlayer",
            "member": {
              "id": 737682,
              "__typename": "Member"
            }
          }
        ],
        "__typename": "Team"
      },
      "session": {
        "id": 123,
        "name": "Summer 2022",
        "year": 2022,
        "__typename": "Session"
      },
      "fees": {
        "amount": 45,
        "tax": 0,
        "total": 45,
        "__typename": "Fees"
      },
      "orderItems": null,
      "results": [
        {
          "homeAway": "HOME",
          "overUnder": 0,
          "forfeits": 0,
          "matchesWon": 5,
          "matchesPlayed": 5,
          "points": {
            "bonus": 4,
            "penalty": 0,
            "won": 12,
            "adjustment": 0,
            "sportsmanship": 0,
            "total": 16,
            "skillLevelViolationAdjustment": 0,
            "__typename": "MatchResultPoints"
          },
          "scores": [
            {
              "id": 85759611,
              "player": {
                "id": 85062951,
                "displayName": "Lou Cirucci",
                "__typename": "EightBallPlayer"
              },
              "matchPositionNumber": 1,
              "playerPosition": 2,
              "skillLevel": 4,
              "eightBallWins": 4,
              "eightOnBreak": 0,
              "eightBallBreakAndRun": 0,
              "nineBallPoints": null,
              "nineOnSnap": null,
              "nineBallBreakAndRun": null,
              "nineBallMatchPointsEarned": null,
              "mastersEightBallWins": null,
              "mastersNineBallWins": null,
              "winLoss": "W",
              "matchForfeited": false,
              "doublesMatch": false,
              "dateTimeStamp": "2022-07-19T18:30:13+00:00",
              "teamSlot": "8A",
              "eightBallMatchPointsEarned": 3,
              "incompleteMatch": false,
              "__typename": "MatchScore"
            },
            {
              "id": 85759612,
              "player": {
                "id": 85319882,
                "displayName": "Jim Barnabei",
                "__typename": "EightBallPlayer"
              },
              "matchPositionNumber": 2,
              "playerPosition": 1,
              "skillLevel": 3,
              "eightBallWins": 2,
              "eightOnBreak": 0,
              "eightBallBreakAndRun": 0,
              "nineBallPoints": null,
              "nineOnSnap": null,
              "nineBallBreakAndRun": null,
              "nineBallMatchPointsEarned": null,
              "mastersEightBallWins": null,
              "mastersNineBallWins": null,
              "winLoss": "W",
              "matchForfeited": false,
              "doublesMatch": false,
              "dateTimeStamp": "2022-07-19T18:30:13+00:00",
              "teamSlot": "8A",
              "eightBallMatchPointsEarned": 2,
              "incompleteMatch": false,
              "__typename": "MatchScore"
            },
            {
              "id": 85759615,
              "player": {
                "id": 85062946,
                "displayName": "Stephen Pressey",
                "__typename": "EightBallPlayer"
              },
              "matchPositionNumber": 3,
              "playerPosition": 2,
              "skillLevel": 4,
              "eightBallWins": 3,
              "eightOnBreak": 0,
              "eightBallBreakAndRun": 0,
              "nineBallPoints": null,
              "nineOnSnap": null,
              "nineBallBreakAndRun": null,
              "nineBallMatchPointsEarned": null,
              "mastersEightBallWins": null,
              "mastersNineBallWins": null,
              "winLoss": "W",
              "matchForfeited": false,
              "doublesMatch": false,
              "dateTimeStamp": "2022-07-19T18:30:13+00:00",
              "teamSlot": "8A",
              "eightBallMatchPointsEarned": 2,
              "incompleteMatch": false,
              "__typename": "MatchScore"
            },
            {
              "id": 85759616,
              "player": {
                "id": 85062952,
                "displayName": "Chet Reklewski",
                "__typename": "EightBallPlayer"
              },
              "matchPositionNumber": 4,
              "playerPosition": 1,
              "skillLevel": 5,
              "eightBallWins": 5,
              "eightOnBreak": 0,
              "eightBallBreakAndRun": 0,
              "nineBallPoints": null,
              "nineOnSnap": null,
              "nineBallBreakAndRun": null,
              "nineBallMatchPointsEarned": null,
              "mastersEightBallWins": null,
              "mastersNineBallWins": null,
              "winLoss": "W",
              "matchForfeited": false,
              "doublesMatch": false,
              "dateTimeStamp": "2022-07-19T18:30:13+00:00",
              "teamSlot": "8A",
              "eightBallMatchPointsEarned": 3,
              "incompleteMatch": false,
              "__typename": "MatchScore"
            },
            {
              "id": 85759618,
              "player": {
                "id": 85062950,
                "displayName": "Mailman Williams",
                "__typename": "EightBallPlayer"
              },
              "matchPositionNumber": 5,
              "playerPosition": 1,
              "skillLevel": 6,
              "eightBallWins": 5,
              "eightOnBreak": 0,
              "eightBallBreakAndRun": 1,
              "nineBallPoints": null,
              "nineOnSnap": null,
              "nineBallBreakAndRun": null,
              "nineBallMatchPointsEarned": null,
              "mastersEightBallWins": null,
              "mastersNineBallWins": null,
              "winLoss": "W",
              "matchForfeited": false,
              "doublesMatch": false,
              "dateTimeStamp": "2022-07-19T18:30:13+00:00",
              "teamSlot": "8A",
              "eightBallMatchPointsEarned": 2,
              "incompleteMatch": false,
              "__typename": "MatchScore"
            }
          ],
          "__typename": "MatchResult"
        },
        {
          "homeAway": "AWAY",
          "overUnder": 0,
          "forfeits": 0,
          "matchesWon": 0,
          "matchesPlayed": 5,
          "points": {
            "bonus": 4,
            "penalty": 0,
            "won": 2,
            "adjustment": 0,
            "sportsmanship": 0,
            "total": 6,
            "skillLevelViolationAdjustment": 0,
            "__typename": "MatchResultPoints"
          },
          "scores": [
            {
              "id": 85759619,
              "player": {
                "id": 85193849,
                "displayName": "John Free-26 Makin",
                "__typename": "EightBallPlayer"
              },
              "matchPositionNumber": 5,
              "playerPosition": 2,
              "skillLevel": 6,
              "eightBallWins": 1,
              "eightOnBreak": 0,
              "eightBallBreakAndRun": 0,
              "nineBallPoints": null,
              "nineOnSnap": null,
              "nineBallBreakAndRun": null,
              "nineBallMatchPointsEarned": null,
              "mastersEightBallWins": null,
              "mastersNineBallWins": null,
              "winLoss": "L",
              "matchForfeited": false,
              "doublesMatch": false,
              "dateTimeStamp": "2022-07-19T18:30:13+00:00",
              "teamSlot": "8D",
              "eightBallMatchPointsEarned": 0,
              "incompleteMatch": false,
              "__typename": "MatchScore"
            },
            {
              "id": 85759617,
              "player": {
                "id": 85193850,
                "displayName": "Larry Bythrow",
                "__typename": "EightBallPlayer"
              },
              "matchPositionNumber": 4,
              "playerPosition": 2,
              "skillLevel": 2,
              "eightBallWins": 0,
              "eightOnBreak": 0,
              "eightBallBreakAndRun": 0,
              "nineBallPoints": null,
              "nineOnSnap": null,
              "nineBallBreakAndRun": null,
              "nineBallMatchPointsEarned": null,
              "mastersEightBallWins": null,
              "mastersNineBallWins": null,
              "winLoss": "L",
              "matchForfeited": false,
              "doublesMatch": false,
              "dateTimeStamp": "2022-07-19T18:30:13+00:00",
              "teamSlot": "8B",
              "eightBallMatchPointsEarned": 0,
              "incompleteMatch": false,
              "__typename": "MatchScore"
            },
            {
              "id": 85759613,
              "player": {
                "id": 85193842,
                "displayName": "JR Geesaman Jr.",
                "__typename": "EightBallPlayer"
              },
              "matchPositionNumber": 2,
              "playerPosition": 2,
              "skillLevel": 3,
              "eightBallWins": 1,
              "eightOnBreak": 0,
              "eightBallBreakAndRun": 0,
              "nineBallPoints": null,
              "nineOnSnap": null,
              "nineBallBreakAndRun": null,
              "nineBallMatchPointsEarned": null,
              "mastersEightBallWins": null,
              "mastersNineBallWins": null,
              "winLoss": "L",
              "matchForfeited": false,
              "doublesMatch": false,
              "dateTimeStamp": "2022-07-19T18:30:13+00:00",
              "teamSlot": "8A",
              "eightBallMatchPointsEarned": 1,
              "incompleteMatch": false,
              "__typename": "MatchScore"
            },
            {
              "id": 85759614,
              "player": {
                "id": 85193841,
                "displayName": "Krystion Geesaman",
                "__typename": "EightBallPlayer"
              },
              "matchPositionNumber": 3,
              "playerPosition": 1,
              "skillLevel": 3,
              "eightBallWins": 1,
              "eightOnBreak": 0,
              "eightBallBreakAndRun": 0,
              "nineBallPoints": null,
              "nineOnSnap": null,
              "nineBallBreakAndRun": null,
              "nineBallMatchPointsEarned": null,
              "mastersEightBallWins": null,
              "mastersNineBallWins": null,
              "winLoss": "L",
              "matchForfeited": false,
              "doublesMatch": false,
              "dateTimeStamp": "2022-07-19T18:30:13+00:00",
              "teamSlot": "8B",
              "eightBallMatchPointsEarned": 1,
              "incompleteMatch": false,
              "__typename": "MatchScore"
            },
            {
              "id": 85759610,
              "player": {
                "id": 85259796,
                "displayName": "Dillon Mills",
                "__typename": "EightBallPlayer"
              },
              "matchPositionNumber": 1,
              "playerPosition": 1,
              "skillLevel": 2,
              "eightBallWins": 0,
              "eightOnBreak": 0,
              "eightBallBreakAndRun": 0,
              "nineBallPoints": null,
              "nineOnSnap": null,
              "nineBallBreakAndRun": null,
              "nineBallMatchPointsEarned": null,
              "mastersEightBallWins": null,
              "mastersNineBallWins": null,
              "winLoss": "L",
              "matchForfeited": false,
              "doublesMatch": false,
              "dateTimeStamp": "2022-07-19T18:30:13+00:00",
              "teamSlot": "8A",
              "eightBallMatchPointsEarned": 0,
              "incompleteMatch": false,
              "__typename": "MatchScore"
            }
          ],
          "__typename": "MatchResult"
        }
      ]
    }
  }
}