{
  "fetchedAt": "2026-05-02T20:41:29.160Z",
  "data": {
    "match": {
      "id": 42830227,
      "isFinalized": true,
      "isTournament": false,
      "tableNumber": null,
      "division": {
        "id": 386505,
        "electronicScoringEnabled": true,
        "__typename": "Division",
        "scheduleInEdit": false,
        "type": "EIGHT"
      },
      "league": {
        "id": 890,
        "esEnabled": true,
        "__typename": "League",
        "name": "APA of South Jersey",
        "currentSessionId": 138,
        "isElectronicPaymentsEnabled": false,
        "country": {
          "id": 1,
          "__typename": "Country"
        }
      },
      "__typename": "Match",
      "type": "EIGHT",
      "startTime": "2024-07-30T19:30:00-04:00",
      "week": 13,
      "isBye": true,
      "isMine": false,
      "isScored": true,
      "scoresheet": null,
      "isPaid": null,
      "timeZone": {
        "id": "169",
        "name": "America/New_York",
        "__typename": "TimeZone"
      },
      "location": {
        "id": 93091,
        "phone": "+16098713231",
        "name": "Edgewater Park Elks 2550",
        "address": {
          "id": 28377,
          "name": "Edgewater Park Elks 2550",
          "address1": "315 Green St.",
          "address2": "",
          "city": "Beverly",
          "zip": "08010",
          "latitude": 40.0516111,
          "longitude": -74.9169864,
          "__typename": "Address"
        },
        "__typename": "HostLocation"
      },
      "home": {
        "id": 12514614,
        "name": "Franks N Beans",
        "number": "07902",
        "isMine": false,
        "league": {
          "id": 890,
          "slug": "southjersey",
          "__typename": "League"
        },
        "division": {
          "id": 386505,
          "type": "EIGHT",
          "__typename": "Division"
        },
        "roster": [
          {
            "id": 88470405,
            "memberNumber": "08204069",
            "displayName": "Timothy Geesaman",
            "matchesWon": 7,
            "matchesPlayed": 10,
            "pa": 0.6333333333333333,
            "ppm": 1.9,
            "skillLevel": 4,
            "__typename": "EightBallPlayer",
            "member": {
              "id": 2753287,
              "__typename": "Member"
            }
          },
          {
            "id": 88470404,
            "memberNumber": "08203400",
            "displayName": "Donald Heal  Jr",
            "matchesWon": 3,
            "matchesPlayed": 9,
            "pa": 0.2962962962962963,
            "ppm": 0.8888888888888888,
            "skillLevel": 4,
            "__typename": "EightBallPlayer",
            "member": {
              "id": 2738025,
              "__typename": "Member"
            }
          },
          {
            "id": 88470407,
            "memberNumber": "08212769",
            "displayName": "John Herman",
            "matchesWon": 4,
            "matchesPlayed": 11,
            "pa": 0.3333333333333333,
            "ppm": 1,
            "skillLevel": 4,
            "__typename": "EightBallPlayer",
            "member": {
              "id": 3169797,
              "__typename": "Member"
            }
          },
          {
            "id": 88470402,
            "memberNumber": "08215468",
            "displayName": "Patrick Daley",
            "matchesWon": 5,
            "matchesPlayed": 6,
            "pa": 0.5555555555555556,
            "ppm": 1.6666666666666667,
            "skillLevel": 7,
            "__typename": "EightBallPlayer",
            "member": {
              "id": 737682,
              "__typename": "Member"
            }
          },
          {
            "id": 88470406,
            "memberNumber": "08208853",
            "displayName": "Krystion Geesaman",
            "matchesWon": 5,
            "matchesPlayed": 6,
            "pa": 0.611111111111111,
            "ppm": 1.8333333333333333,
            "skillLevel": 5,
            "__typename": "EightBallPlayer",
            "member": {
              "id": 2942824,
              "__typename": "Member"
            }
          },
          {
            "id": 88470409,
            "memberNumber": "08213258",
            "displayName": "Rafael Aponte Jr",
            "matchesWon": 3,
            "matchesPlayed": 9,
            "pa": 0.25925925925925924,
            "ppm": 0.7777777777777778,
            "skillLevel": 6,
            "__typename": "EightBallPlayer",
            "member": {
              "id": 2907361,
              "__typename": "Member"
            }
          },
          {
            "id": 88470403,
            "memberNumber": "08211124",
            "displayName": "Mike Nolan",
            "matchesWon": 6,
            "matchesPlayed": 8,
            "pa": 0.625,
            "ppm": 1.875,
            "skillLevel": 4,
            "__typename": "EightBallPlayer",
            "member": {
              "id": 2530267,
              "__typename": "Member"
            }
          },
          {
            "id": 88470408,
            "memberNumber": "08207118",
            "displayName": "Larry Bythrow",
            "matchesWon": 4,
            "matchesPlayed": 6,
            "pa": 0.5555555555555556,
            "ppm": 1.6666666666666667,
            "skillLevel": 3,
            "__typename": "EightBallPlayer",
            "member": {
              "id": 3220246,
              "__typename": "Member"
            }
          }
        ],
        "__typename": "Team"
      },
      "away": {
        "id": 12514852,
        "name": "Bye",
        "number": "07906",
        "isMine": false,
        "league": {
          "id": 890,
          "slug": "southjersey",
          "__typename": "League"
        },
        "division": {
          "id": 386505,
          "type": "EIGHT",
          "__typename": "Division"
        },
        "roster": [],
        "__typename": "Team"
      },
      "session": {
        "id": 133,
        "name": "Summer 2024",
        "year": 2024,
        "__typename": "Session"
      },
      "fees": {
        "amount": 45,
        "tax": 0,
        "total": 45,
        "__typename": "Fees"
      },
      "orderItems": null,
      "results": [
        {
          "homeAway": "HOME",
          "overUnder": 0,
          "forfeits": 0,
          "matchesWon": 0,
          "matchesPlayed": 0,
          "points": {
            "bonus": 4,
            "penalty": 0,
            "won": 8,
            "adjustment": 0,
            "sportsmanship": 0,
            "total": 12,
            "skillLevelViolationAdjustment": 0,
            "__typename": "MatchResultPoints"
          },
          "scores": [],
          "__typename": "MatchResult"
        },
        {
          "homeAway": "AWAY",
          "overUnder": 0,
          "forfeits": 0,
          "matchesWon": 0,
          "matchesPlayed": 0,
          "points": {
            "bonus": 0,
            "penalty": 0,
            "won": 0,
            "adjustment": 0,
            "sportsmanship": 0,
            "total": 0,
            "skillLevelViolationAdjustment": 0,
            "__typename": "MatchResultPoints"
          },
          "scores": [],
          "__typename": "MatchResult"
        }
      ]
    }
  }
}