{
  "fetchedAt": "2026-05-04T22:01:25.722Z",
  "data": {
    "aliasSessionStats": {
      "alias": {
        "id": 3123306,
        "league": {
          "id": 890,
          "currentSessionId": 138,
          "slug": "southjersey",
          "__typename": "League"
        },
        "players": [
          {
            "id": 91261548,
            "team": {
              "id": 12894669,
              "name": "The Office",
              "number": "06809",
              "active": true,
              "__typename": "Team"
            },
            "pa": 0.20833333333333334,
            "ppm": 0.625,
            "eightBallMatchPointsEarned": 5,
            "matchesWon": 1,
            "matchesPlayed": 8,
            "eightBallBreakAndRuns": 0,
            "eightOnBreaks": 0,
            "miniSlams": 0,
            "rackless": 0,
            "__typename": "EightBallPlayer"
          },
          {
            "id": 91095233,
            "team": {
              "id": 12858096,
              "name": "The Office",
              "number": "06802",
              "active": true,
              "__typename": "Team"
            },
            "pa": 0.13333333333333333,
            "ppm": 0.4,
            "eightBallMatchPointsEarned": 2,
            "matchesWon": 0,
            "matchesPlayed": 5,
            "eightBallBreakAndRuns": 0,
            "eightOnBreaks": 0,
            "miniSlams": 0,
            "rackless": 0,
            "__typename": "EightBallPlayer"
          },
          {
            "id": 88902027,
            "team": {
              "id": 12576460,
              "name": "The Office",
              "number": "06809",
              "active": true,
              "__typename": "Team"
            },
            "pa": 0.16666666666666666,
            "ppm": 0.5,
            "eightBallMatchPointsEarned": 4,
            "matchesWon": 2,
            "matchesPlayed": 8,
            "eightBallBreakAndRuns": 0,
            "eightOnBreaks": 0,
            "miniSlams": 0,
            "rackless": 0,
            "__typename": "EightBallPlayer"
          },
          {
            "id": 88470185,
            "team": {
              "id": 12514586,
              "name": "The Office",
              "number": "05707",
              "active": true,
              "__typename": "Team"
            },
            "pa": 0.375,
            "ppm": 1.125,
            "eightBallMatchPointsEarned": 9,
            "matchesWon": 4,
            "matchesPlayed": 8,
            "eightBallBreakAndRuns": 0,
            "eightOnBreaks": 0,
            "miniSlams": 0,
            "rackless": 0,
            "__typename": "EightBallPlayer"
          },
          {
            "id": 88020141,
            "team": {
              "id": 12417151,
              "name": "The Office",
              "number": "06815",
              "active": true,
              "__typename": "Team"
            },
            "pa": 0.26666666666666666,
            "ppm": 0.8,
            "eightBallMatchPointsEarned": 8,
            "matchesWon": 3,
            "matchesPlayed": 10,
            "eightBallBreakAndRuns": 0,
            "eightOnBreaks": 0,
            "miniSlams": 0,
            "rackless": 0,
            "__typename": "EightBallPlayer"
          }
        ],
        "__typename": "Alias"
      }
    },
    "aliasSessionStatsDropdown": {
      "alias": {
        "id": 3123306,
        "sessions": [
          {
            "id": 138,
            "name": "Spring 2026",
            "__typename": "Session"
          },
          {
            "id": 137,
            "name": "Fall 2025",
            "__typename": "Session"
          },
          {
            "id": 134,
            "name": "Fall 2024",
            "__typename": "Session"
          },
          {
            "id": 133,
            "name": "Summer 2024",
            "__typename": "Session"
          },
          {
            "id": 132,
            "name": "Spring 2024",
            "__typename": "Session"
          }
        ],
        "__typename": "Alias"
      }
    },
    "getEightBallStats": {
      "alias": {
        "players": [
          {
            "id": 91261548,
            "session": {
              "id": 138,
              "__typename": "Session"
            },
            "eightOnBreaks": 0,
            "eightBallBreakAndRuns": 0,
            "rackless": 0,
            "miniSlams": 0,
            "__typename": "EightBallPlayer"
          },
          {
            "id": 91095233,
            "session": {
              "id": 137,
              "__typename": "Session"
            },
            "eightOnBreaks": 0,
            "eightBallBreakAndRuns": 0,
            "rackless": 0,
            "miniSlams": 0,
            "__typename": "EightBallPlayer"
          },
          {
            "id": 88902027,
            "session": {
              "id": 134,
              "__typename": "Session"
            },
            "eightOnBreaks": 0,
            "eightBallBreakAndRuns": 0,
            "rackless": 0,
            "miniSlams": 0,
            "__typename": "EightBallPlayer"
          },
          {
            "id": 88471892,
            "session": {
              "id": 133,
              "__typename": "Session"
            },
            "nineOnSnaps": 0,
            "nineBallBreakAndRuns": 0,
            "miniSlams": 0,
            "skunks": 0,
            "__typename": "NineBallPlayer"
          },
          {
            "id": 88470185,
            "session": {
              "id": 133,
              "__typename": "Session"
            },
            "eightOnBreaks": 0,
            "eightBallBreakAndRuns": 0,
            "rackless": 0,
            "miniSlams": 0,
            "__typename": "EightBallPlayer"
          },
          {
            "id": 87790093,
            "session": {
              "id": 132,
              "__typename": "Session"
            },
            "nineOnSnaps": 0,
            "nineBallBreakAndRuns": 0,
            "miniSlams": 0,
            "skunks": 0,
            "__typename": "NineBallPlayer"
          },
          {
            "id": 88020141,
            "session": {
              "id": 132,
              "__typename": "Session"
            },
            "eightOnBreaks": 0,
            "eightBallBreakAndRuns": 0,
            "rackless": 0,
            "miniSlams": 0,
            "__typename": "EightBallPlayer"
          },
          {
            "id": 87381951,
            "session": {
              "id": 130,
              "__typename": "Session"
            },
            "nineOnSnaps": 1,
            "nineBallBreakAndRuns": 0,
            "miniSlams": 0,
            "skunks": 0,
            "__typename": "NineBallPlayer"
          }
        ],
        "id": 3123306,
        "displayName": "Christopher Carter",
        "EightBallStats": [
          {
            "id": 803123306,
            "matchesWon": 13,
            "matchesPlayed": 46,
            "CLA": 4,
            "defensiveShotAvg": 0.74,
            "matchCountForLastTwoYrs": 36,
            "lastPlayed": "2026-04-28T00:00:00Z",
            "__typename": "EightBallLifetimeStatistics"
          }
        ],
        "NineBallStats": [
          {
            "id": 903123306,
            "matchesWon": 18,
            "matchesPlayed": 30,
            "CLA": 0,
            "defensiveShotAvg": 0.5,
            "matchCountForLastTwoYrs": 4,
            "lastPlayed": "2024-06-10T00:00:00Z",
            "__typename": "NineBallLifetimeStatistics"
          }
        ],
        "__typename": "Alias"
      }
    },
    "getMembershipHistory": {
      "alias": {
        "id": 3123306,
        "member": {
          "id": 3306967,
          "consecutiveYearsPlayed": 4,
          "membershipHistory": [
            {
              "id": 6986910,
              "year": 2023,
              "leaguePaidIn": {
                "id": 890,
                "name": "APA of South Jersey",
                "salutation": "Dave Piotrowski & Michelle Miller",
                "__typename": "League"
              },
              "__typename": "MembershipHistory"
            },
            {
              "id": 7013423,
              "year": 2024,
              "leaguePaidIn": {
                "id": 890,
                "name": "APA of South Jersey",
                "salutation": "Dave Piotrowski & Michelle Miller",
                "__typename": "League"
              },
              "__typename": "MembershipHistory"
            },
            {
              "id": 7549403,
              "year": 2025,
              "leaguePaidIn": {
                "id": 890,
                "name": "APA of South Jersey",
                "salutation": "Dave Piotrowski & Michelle Miller",
                "__typename": "League"
              },
              "__typename": "MembershipHistory"
            },
            {
              "id": 7590767,
              "year": 2026,
              "leaguePaidIn": {
                "id": 890,
                "name": "APA of South Jersey",
                "salutation": "Dave Piotrowski & Michelle Miller",
                "__typename": "League"
              },
              "__typename": "MembershipHistory"
            }
          ],
          "__typename": "Member"
        },
        "__typename": "Alias"
      }
    }
  }
}