{
  "fetchedAt": "2026-05-02T20:21:39.403Z",
  "data": {
    "teamPage": {
      "team": {
        "id": 12417219,
        "name": "Eight Men Out",
        "number": "06806",
        "isTied": false,
        "standing": 5,
        "division": {
          "id": 377837,
          "name": "Gl-68",
          "number": "068",
          "timeOfPlay": "1900-01-01T19:30:00Z",
          "nightOfPlay": "Tuesday",
          "format": "8-Ball Open",
          "state": "PAST",
          "isTournament": false,
          "tournament": null,
          "__typename": "Division"
        },
        "location": {
          "id": 90042,
          "name": "Wilson's Pub",
          "address": {
            "id": 40206,
            "name": "Wilson's Pub",
            "__typename": "Address"
          },
          "__typename": "HostLocation"
        },
        "session": {
          "id": 132,
          "name": "Spring 2024",
          "__typename": "Session"
        },
        "league": {
          "id": 890,
          "slug": "southjersey",
          "__typename": "League"
        },
        "__typename": "Team"
      }
    },
    "teamRoster": {
      "team": {
        "id": 12417219,
        "name": "Eight Men Out",
        "number": "06806",
        "league": {
          "id": 890,
          "slug": "southjersey",
          "__typename": "League"
        },
        "division": {
          "id": 377837,
          "type": "EIGHT",
          "__typename": "Division"
        },
        "roster": [
          {
            "id": 87789680,
            "memberNumber": "08203833",
            "displayName": "Peter Johnson V",
            "matchesWon": 7,
            "matchesPlayed": 12,
            "pa": 0.5277777777777778,
            "ppm": 1.5833333333333333,
            "skillLevel": 3,
            "__typename": "EightBallPlayer",
            "member": {
              "id": 3168689,
              "__typename": "Member"
            }
          },
          {
            "id": 87789679,
            "memberNumber": "08212765",
            "displayName": "Pete Johnson IV",
            "matchesWon": 5,
            "matchesPlayed": 12,
            "pa": 0.3333333333333333,
            "ppm": 1,
            "skillLevel": 4,
            "__typename": "EightBallPlayer",
            "member": {
              "id": 747020,
              "__typename": "Member"
            }
          },
          {
            "id": 87789681,
            "memberNumber": "08203835",
            "displayName": "Meghan Johnson",
            "matchesWon": 6,
            "matchesPlayed": 10,
            "pa": 0.5333333333333333,
            "ppm": 1.6,
            "skillLevel": 3,
            "__typename": "EightBallPlayer",
            "member": {
              "id": 3168757,
              "__typename": "Member"
            }
          },
          {
            "id": 87789678,
            "memberNumber": "08212737",
            "displayName": "Steven Johnson",
            "matchesWon": 4,
            "matchesPlayed": 10,
            "pa": 0.3,
            "ppm": 0.9,
            "skillLevel": 4,
            "__typename": "EightBallPlayer",
            "member": {
              "id": 818783,
              "__typename": "Member"
            }
          },
          {
            "id": 87789683,
            "memberNumber": "08203907",
            "displayName": "Robert Wiscount",
            "matchesWon": 4,
            "matchesPlayed": 8,
            "pa": 0.5,
            "ppm": 1.5,
            "skillLevel": 3,
            "__typename": "EightBallPlayer",
            "member": {
              "id": 3175746,
              "__typename": "Member"
            }
          },
          {
            "id": 87789682,
            "memberNumber": "08203852",
            "displayName": "Anand Patel",
            "matchesWon": 5,
            "matchesPlayed": 9,
            "pa": 0.48148148148148145,
            "ppm": 1.4444444444444444,
            "skillLevel": 3,
            "__typename": "EightBallPlayer",
            "member": {
              "id": 3175408,
              "__typename": "Member"
            }
          },
          {
            "id": 87789677,
            "memberNumber": "08215468",
            "displayName": "Patrick Daley",
            "matchesWon": 2,
            "matchesPlayed": 4,
            "pa": 0.4166666666666667,
            "ppm": 1.25,
            "skillLevel": 7,
            "__typename": "EightBallPlayer",
            "member": {
              "id": 737682,
              "__typename": "Member"
            }
          },
          {
            "id": 87789684,
            "memberNumber": "08211481",
            "displayName": "Aaron Bickford",
            "matchesWon": 8,
            "matchesPlayed": 14,
            "pa": 0.6190476190476191,
            "ppm": 1.8571428571428572,
            "skillLevel": 3,
            "__typename": "EightBallPlayer",
            "member": {
              "id": 3253364,
              "__typename": "Member"
            }
          }
        ],
        "__typename": "Team"
      }
    },
    "teamSchedule": {
      "team": {
        "id": 12417219,
        "sessionBonusPoints": 0,
        "sessionPoints": 190,
        "sessionTotalPoints": 190,
        "division": {
          "id": 377837,
          "isTournament": false,
          "__typename": "Division"
        },
        "matches": [
          {
            "week": 1,
            "type": "EIGHT",
            "id": 41560241,
            "isBye": false,
            "status": "COMPLETED",
            "scoresheet": null,
            "startTime": "2024-01-02T19:30:00-05:00",
            "isMine": true,
            "isPaid": false,
            "isScored": true,
            "isFinalized": true,
            "isPlayoff": false,
            "description": "",
            "tableNumber": null,
            "results": [
              {
                "homeAway": "HOME",
                "points": {
                  "total": 11,
                  "__typename": "MatchResultPoints"
                },
                "__typename": "MatchResult"
              },
              {
                "homeAway": "AWAY",
                "points": {
                  "total": 10,
                  "__typename": "MatchResultPoints"
                },
                "__typename": "MatchResult"
              }
            ],
            "timeZone": {
              "id": "169",
              "name": "America/New_York",
              "__typename": "TimeZone"
            },
            "location": {
              "id": 90042,
              "name": "Wilson's Pub",
              "address": {
                "id": 40206,
                "name": "Wilson's Pub",
                "__typename": "Address"
              },
              "__typename": "HostLocation"
            },
            "home": {
              "id": 12417219,
              "name": "Eight Men Out",
              "number": "06806",
              "isMine": true,
              "__typename": "Team"
            },
            "away": {
              "id": 12416786,
              "name": "Lights Out",
              "number": "06805",
              "isMine": false,
              "__typename": "Team"
            },
            "league": {
              "id": 890,
              "isMine": true,
              "slug": "southjersey",
              "isElectronicPaymentsEnabled": false,
              "__typename": "League"
            },
            "orderItems": [],
            "division": {
              "id": 377837,
              "scheduleInEdit": false,
              "isTournament": false,
              "__typename": "Division"
            },
            "__typename": "Match"
          },
          {
            "week": 2,
            "type": "EIGHT",
            "id": 41560248,
            "isBye": false,
            "status": "COMPLETED",
            "scoresheet": null,
            "startTime": "2024-01-09T19:30:00-05:00",
            "isMine": true,
            "isPaid": false,
            "isScored": true,
            "isFinalized": true,
            "isPlayoff": false,
            "description": "",
            "tableNumber": null,
            "results": [
              {
                "homeAway": "HOME",
                "points": {
                  "total": 12,
                  "__typename": "MatchResultPoints"
                },
                "__typename": "MatchResult"
              },
              {
                "homeAway": "AWAY",
                "points": {
                  "total": 11,
                  "__typename": "MatchResultPoints"
                },
                "__typename": "MatchResult"
              }
            ],
            "timeZone": {
              "id": "169",
              "name": "America/New_York",
              "__typename": "TimeZone"
            },
            "location": {
              "id": 90042,
              "name": "Wilson's Pub",
              "address": {
                "id": 40206,
                "name": "Wilson's Pub",
                "__typename": "Address"
              },
              "__typename": "HostLocation"
            },
            "home": {
              "id": 12417219,
              "name": "Eight Men Out",
              "number": "06806",
              "isMine": true,
              "__typename": "Team"
            },
            "away": {
              "id": 12417050,
              "name": "Poke & Choke",
              "number": "06803",
              "isMine": false,
              "__typename": "Team"
            },
            "league": {
              "id": 890,
              "isMine": true,
              "slug": "southjersey",
              "isElectronicPaymentsEnabled": false,
              "__typename": "League"
            },
            "orderItems": [],
            "division": {
              "id": 377837,
              "scheduleInEdit": false,
              "isTournament": false,
              "__typename": "Division"
            },
            "__typename": "Match"
          },
          {
            "week": 3,
            "type": "EIGHT",
            "id": 41560255,
            "isBye": false,
            "status": "COMPLETED",
            "scoresheet": null,
            "startTime": "2024-01-16T19:30:00-05:00",
            "isMine": true,
            "isPaid": false,
            "isScored": true,
            "isFinalized": true,
            "isPlayoff": false,
            "description": "",
            "tableNumber": null,
            "results": [
              {
                "homeAway": "HOME",
                "points": {
                  "total": 9,
                  "__typename": "MatchResultPoints"
                },
                "__typename": "MatchResult"
              },
              {
                "homeAway": "AWAY",
                "points": {
                  "total": 11,
                  "__typename": "MatchResultPoints"
                },
                "__typename": "MatchResult"
              }
            ],
            "timeZone": {
              "id": "169",
              "name": "America/New_York",
              "__typename": "TimeZone"
            },
            "location": {
              "id": 88174,
              "name": "National Park Pub & Grill",
              "address": {
                "id": 72204,
                "name": "National Park Pub & Grill",
                "__typename": "Address"
              },
              "__typename": "HostLocation"
            },
            "home": {
              "id": 12416783,
              "name": "Rack Pack",
              "number": "06801",
              "isMine": false,
              "__typename": "Team"
            },
            "away": {
              "id": 12417219,
              "name": "Eight Men Out",
              "number": "06806",
              "isMine": true,
              "__typename": "Team"
            },
            "league": {
              "id": 890,
              "isMine": true,
              "slug": "southjersey",
              "isElectronicPaymentsEnabled": false,
              "__typename": "League"
            },
            "orderItems": [],
            "division": {
              "id": 377837,
              "scheduleInEdit": false,
              "isTournament": false,
              "__typename": "Division"
            },
            "__typename": "Match"
          },
          {
            "week": 4,
            "type": "EIGHT",
            "id": 41560270,
            "isBye": false,
            "status": "COMPLETED",
            "scoresheet": null,
            "startTime": "2024-01-23T19:30:00-05:00",
            "isMine": true,
            "isPaid": false,
            "isScored": true,
            "isFinalized": true,
            "isPlayoff": false,
            "description": "",
            "tableNumber": null,
            "results": [
              {
                "homeAway": "HOME",
                "points": {
                  "total": 7,
                  "__typename": "MatchResultPoints"
                },
                "__typename": "MatchResult"
              },
              {
                "homeAway": "AWAY",
                "points": {
                  "total": 14,
                  "__typename": "MatchResultPoints"
                },
                "__typename": "MatchResult"
              }
            ],
            "timeZone": {
              "id": "169",
              "name": "America/New_York",
              "__typename": "TimeZone"
            },
            "location": {
              "id": 81473,
              "name": "The Office",
              "address": {
                "id": 32203,
                "name": "The Office",
                "__typename": "Address"
              },
              "__typename": "HostLocation"
            },
            "home": {
              "id": 12417151,
              "name": "The Office",
              "number": "06815",
              "isMine": false,
              "__typename": "Team"
            },
            "away": {
              "id": 12417219,
              "name": "Eight Men Out",
              "number": "06806",
              "isMine": true,
              "__typename": "Team"
            },
            "league": {
              "id": 890,
              "isMine": true,
              "slug": "southjersey",
              "isElectronicPaymentsEnabled": false,
              "__typename": "League"
            },
            "orderItems": [],
            "division": {
              "id": 377837,
              "scheduleInEdit": false,
              "isTournament": false,
              "__typename": "Division"
            },
            "__typename": "Match"
          },
          {
            "week": 5,
            "type": "EIGHT",
            "id": 41560277,
            "isBye": false,
            "status": "COMPLETED",
            "scoresheet": null,
            "startTime": "2024-01-30T19:30:00-05:00",
            "isMine": true,
            "isPaid": false,
            "isScored": true,
            "isFinalized": true,
            "isPlayoff": false,
            "description": "",
            "tableNumber": null,
            "results": [
              {
                "homeAway": "HOME",
                "points": {
                  "total": 7,
                  "__typename": "MatchResultPoints"
                },
                "__typename": "MatchResult"
              },
              {
                "homeAway": "AWAY",
                "points": {
                  "total": 15,
                  "__typename": "MatchResultPoints"
                },
                "__typename": "MatchResult"
              }
            ],
            "timeZone": {
              "id": "169",
              "name": "America/New_York",
              "__typename": "TimeZone"
            },
            "location": {
              "id": 68922,
              "name": "Bellmawr V.FW. 9563",
              "address": {
                "id": 80538,
                "name": "Bellmawr V.FW. 9563",
                "__typename": "Address"
              },
              "__typename": "HostLocation"
            },
            "home": {
              "id": 12417441,
              "name": "Bellmawr VFW",
              "number": "06813",
              "isMine": false,
              "__typename": "Team"
            },
            "away": {
              "id": 12417219,
              "name": "Eight Men Out",
              "number": "06806",
              "isMine": true,
              "__typename": "Team"
            },
            "league": {
              "id": 890,
              "isMine": true,
              "slug": "southjersey",
              "isElectronicPaymentsEnabled": false,
              "__typename": "League"
            },
            "orderItems": [],
            "division": {
              "id": 377837,
              "scheduleInEdit": false,
              "isTournament": false,
              "__typename": "Division"
            },
            "__typename": "Match"
          },
          {
            "week": 6,
            "type": "EIGHT",
            "id": 41560284,
            "isBye": false,
            "status": "COMPLETED",
            "scoresheet": null,
            "startTime": "2024-02-06T19:30:00-05:00",
            "isMine": true,
            "isPaid": false,
            "isScored": true,
            "isFinalized": true,
            "isPlayoff": false,
            "description": "",
            "tableNumber": null,
            "results": [
              {
                "homeAway": "HOME",
                "points": {
                  "total": 11,
                  "__typename": "MatchResultPoints"
                },
                "__typename": "MatchResult"
              },
              {
                "homeAway": "AWAY",
                "points": {
                  "total": 12,
                  "__typename": "MatchResultPoints"
                },
                "__typename": "MatchResult"
              }
            ],
            "timeZone": {
              "id": "169",
              "name": "America/New_York",
              "__typename": "TimeZone"
            },
            "location": {
              "id": 90042,
              "name": "Wilson's Pub",
              "address": {
                "id": 40206,
                "name": "Wilson's Pub",
                "__typename": "Address"
              },
              "__typename": "HostLocation"
            },
            "home": {
              "id": 12417219,
              "name": "Eight Men Out",
              "number": "06806",
              "isMine": true,
              "__typename": "Team"
            },
            "away": {
              "id": 12417425,
              "name": "Break 8 Away",
              "number": "06811",
              "isMine": false,
              "__typename": "Team"
            },
            "league": {
              "id": 890,
              "isMine": true,
              "slug": "southjersey",
              "isElectronicPaymentsEnabled": false,
              "__typename": "League"
            },
            "orderItems": [],
            "division": {
              "id": 377837,
              "scheduleInEdit": false,
              "isTournament": false,
              "__typename": "Division"
            },
            "__typename": "Match"
          },
          {
            "week": 7,
            "type": "EIGHT",
            "id": 41560291,
            "isBye": false,
            "status": "COMPLETED",
            "scoresheet": null,
            "startTime": "2024-02-13T19:30:00-05:00",
            "isMine": true,
            "isPaid": false,
            "isScored": true,
            "isFinalized": true,
            "isPlayoff": false,
            "description": "",
            "tableNumber": null,
            "results": [
              {
                "homeAway": "HOME",
                "points": {
                  "total": 7,
                  "__typename": "MatchResultPoints"
                },
                "__typename": "MatchResult"
              },
              {
                "homeAway": "AWAY",
                "points": {
                  "total": 14,
                  "__typename": "MatchResultPoints"
                },
                "__typename": "MatchResult"
              }
            ],
            "timeZone": {
              "id": "169",
              "name": "America/New_York",
              "__typename": "TimeZone"
            },
            "location": {
              "id": 113653,
              "name": "Spread Eagle Tavern",
              "address": {
                "id": 75396,
                "name": "Spread Eagle Tavern",
                "__typename": "Address"
              },
              "__typename": "HostLocation"
            },
            "home": {
              "id": 12431987,
              "name": "Spread 'em Wider",
              "number": "06809",
              "isMine": false,
              "__typename": "Team"
            },
            "away": {
              "id": 12417219,
              "name": "Eight Men Out",
              "number": "06806",
              "isMine": true,
              "__typename": "Team"
            },
            "league": {
              "id": 890,
              "isMine": true,
              "slug": "southjersey",
              "isElectronicPaymentsEnabled": false,
              "__typename": "League"
            },
            "orderItems": [],
            "division": {
              "id": 377837,
              "scheduleInEdit": false,
              "isTournament": false,
              "__typename": "Division"
            },
            "__typename": "Match"
          },
          {
            "week": 8,
            "type": "EIGHT",
            "id": 41560298,
            "isBye": false,
            "status": "COMPLETED",
            "scoresheet": null,
            "startTime": "2024-02-20T19:30:00-05:00",
            "isMine": true,
            "isPaid": false,
            "isScored": true,
            "isFinalized": true,
            "isPlayoff": false,
            "description": "",
            "tableNumber": null,
            "results": [
              {
                "homeAway": "HOME",
                "points": {
                  "total": 7,
                  "__typename": "MatchResultPoints"
                },
                "__typename": "MatchResult"
              },
              {
                "homeAway": "AWAY",
                "points": {
                  "total": 16,
                  "__typename": "MatchResultPoints"
                },
                "__typename": "MatchResult"
              }
            ],
            "timeZone": {
              "id": "169",
              "name": "America/New_York",
              "__typename": "TimeZone"
            },
            "location": {
              "id": 90042,
              "name": "Wilson's Pub",
              "address": {
                "id": 40206,
                "name": "Wilson's Pub",
                "__typename": "Address"
              },
              "__typename": "HostLocation"
            },
            "home": {
              "id": 12417219,
              "name": "Eight Men Out",
              "number": "06806",
              "isMine": true,
              "__typename": "Team"
            },
            "away": {
              "id": 12417396,
              "name": "Here We Go!",
              "number": "06807",
              "isMine": false,
              "__typename": "Team"
            },
            "league": {
              "id": 890,
              "isMine": true,
              "slug": "southjersey",
              "isElectronicPaymentsEnabled": false,
              "__typename": "League"
            },
            "orderItems": [],
            "division": {
              "id": 377837,
              "scheduleInEdit": false,
              "isTournament": false,
              "__typename": "Division"
            },
            "__typename": "Match"
          },
          {
            "week": 9,
            "type": "EIGHT",
            "id": 41560306,
            "isBye": false,
            "status": "COMPLETED",
            "scoresheet": null,
            "startTime": "2024-02-27T19:30:00-05:00",
            "isMine": true,
            "isPaid": false,
            "isScored": true,
            "isFinalized": true,
            "isPlayoff": false,
            "description": "",
            "tableNumber": null,
            "results": [
              {
                "homeAway": "HOME",
                "points": {
                  "total": 11,
                  "__typename": "MatchResultPoints"
                },
                "__typename": "MatchResult"
              },
              {
                "homeAway": "AWAY",
                "points": {
                  "total": 12,
                  "__typename": "MatchResultPoints"
                },
                "__typename": "MatchResult"
              }
            ],
            "timeZone": {
              "id": "169",
              "name": "America/New_York",
              "__typename": "TimeZone"
            },
            "location": {
              "id": 114604,
              "name": "Nero's Pub",
              "address": {
                "id": 77124,
                "name": "Nero's Pub",
                "__typename": "Address"
              },
              "__typename": "HostLocation"
            },
            "home": {
              "id": 12417335,
              "name": "88 Stacked",
              "number": "06808",
              "isMine": false,
              "__typename": "Team"
            },
            "away": {
              "id": 12417219,
              "name": "Eight Men Out",
              "number": "06806",
              "isMine": true,
              "__typename": "Team"
            },
            "league": {
              "id": 890,
              "isMine": true,
              "slug": "southjersey",
              "isElectronicPaymentsEnabled": false,
              "__typename": "League"
            },
            "orderItems": [],
            "division": {
              "id": 377837,
              "scheduleInEdit": false,
              "isTournament": false,
              "__typename": "Division"
            },
            "__typename": "Match"
          },
          {
            "week": 10,
            "type": "EIGHT",
            "id": 41560314,
            "isBye": false,
            "status": "COMPLETED",
            "scoresheet": null,
            "startTime": "2024-03-05T19:30:00-05:00",
            "isMine": true,
            "isPaid": false,
            "isScored": true,
            "isFinalized": true,
            "isPlayoff": false,
            "description": "",
            "tableNumber": null,
            "results": [
              {
                "homeAway": "HOME",
                "points": {
                  "total": 11,
                  "__typename": "MatchResultPoints"
                },
                "__typename": "MatchResult"
              },
              {
                "homeAway": "AWAY",
                "points": {
                  "total": 10,
                  "__typename": "MatchResultPoints"
                },
                "__typename": "MatchResult"
              }
            ],
            "timeZone": {
              "id": "169",
              "name": "America/New_York",
              "__typename": "TimeZone"
            },
            "location": {
              "id": 113653,
              "name": "Spread Eagle Tavern",
              "address": {
                "id": 75396,
                "name": "Spread Eagle Tavern",
                "__typename": "Address"
              },
              "__typename": "HostLocation"
            },
            "home": {
              "id": 12416993,
              "name": "Everybody Loves Raymond",
              "number": "06812",
              "isMine": false,
              "__typename": "Team"
            },
            "away": {
              "id": 12417219,
              "name": "Eight Men Out",
              "number": "06806",
              "isMine": true,
              "__typename": "Team"
            },
            "league": {
              "id": 890,
              "isMine": true,
              "slug": "southjersey",
              "isElectronicPaymentsEnabled": false,
              "__typename": "League"
            },
            "orderItems": [],
            "division": {
              "id": 377837,
              "scheduleInEdit": false,
              "isTournament": false,
              "__typename": "Division"
            },
            "__typename": "Match"
          },
          {
            "week": 11,
            "type": "EIGHT",
            "id": 41560322,
            "isBye": true,
            "status": "COMPLETED",
            "scoresheet": null,
            "startTime": "2024-03-12T19:30:00-04:00",
            "isMine": true,
            "isPaid": false,
            "isScored": true,
            "isFinalized": true,
            "isPlayoff": false,
            "description": "",
            "tableNumber": null,
            "results": [
              {
                "homeAway": "HOME",
                "points": {
                  "total": 0,
                  "__typename": "MatchResultPoints"
                },
                "__typename": "MatchResult"
              },
              {
                "homeAway": "AWAY",
                "points": {
                  "total": 12,
                  "__typename": "MatchResultPoints"
                },
                "__typename": "MatchResult"
              }
            ],
            "timeZone": {
              "id": "169",
              "name": "America/New_York",
              "__typename": "TimeZone"
            },
            "location": {
              "id": 87357,
              "name": "No Match This Week",
              "address": null,
              "__typename": "HostLocation"
            },
            "home": {
              "id": 12417334,
              "name": "Bye",
              "number": "06816",
              "isMine": false,
              "__typename": "Team"
            },
            "away": {
              "id": 12417219,
              "name": "Eight Men Out",
              "number": "06806",
              "isMine": true,
              "__typename": "Team"
            },
            "league": {
              "id": 890,
              "isMine": true,
              "slug": "southjersey",
              "isElectronicPaymentsEnabled": false,
              "__typename": "League"
            },
            "orderItems": [],
            "division": {
              "id": 377837,
              "scheduleInEdit": false,
              "isTournament": false,
              "__typename": "Division"
            },
            "__typename": "Match"
          },
          {
            "week": 12,
            "type": "EIGHT",
            "id": 41560330,
            "isBye": false,
            "status": "COMPLETED",
            "scoresheet": null,
            "startTime": "2024-03-19T19:30:00-04:00",
            "isMine": true,
            "isPaid": false,
            "isScored": true,
            "isFinalized": true,
            "isPlayoff": false,
            "description": "",
            "tableNumber": null,
            "results": [
              {
                "homeAway": "HOME",
                "points": {
                  "total": 9,
                  "__typename": "MatchResultPoints"
                },
                "__typename": "MatchResult"
              },
              {
                "homeAway": "AWAY",
                "points": {
                  "total": 12,
                  "__typename": "MatchResultPoints"
                },
                "__typename": "MatchResult"
              }
            ],
            "timeZone": {
              "id": "169",
              "name": "America/New_York",
              "__typename": "TimeZone"
            },
            "location": {
              "id": 90042,
              "name": "Wilson's Pub",
              "address": {
                "id": 40206,
                "name": "Wilson's Pub",
                "__typename": "Address"
              },
              "__typename": "HostLocation"
            },
            "home": {
              "id": 12417219,
              "name": "Eight Men Out",
              "number": "06806",
              "isMine": true,
              "__typename": "Team"
            },
            "away": {
              "id": 12416939,
              "name": "8 Balls for Sale",
              "number": "06804",
              "isMine": false,
              "__typename": "Team"
            },
            "league": {
              "id": 890,
              "isMine": true,
              "slug": "southjersey",
              "isElectronicPaymentsEnabled": false,
              "__typename": "League"
            },
            "orderItems": [],
            "division": {
              "id": 377837,
              "scheduleInEdit": false,
              "isTournament": false,
              "__typename": "Division"
            },
            "__typename": "Match"
          },
          {
            "week": 13,
            "type": "EIGHT",
            "id": 41560336,
            "isBye": false,
            "status": "COMPLETED",
            "scoresheet": null,
            "startTime": "2024-03-26T19:30:00-04:00",
            "isMine": true,
            "isPaid": false,
            "isScored": true,
            "isFinalized": true,
            "isPlayoff": false,
            "description": "",
            "tableNumber": null,
            "results": [
              {
                "homeAway": "HOME",
                "points": {
                  "total": 13,
                  "__typename": "MatchResultPoints"
                },
                "__typename": "MatchResult"
              },
              {
                "homeAway": "AWAY",
                "points": {
                  "total": 9,
                  "__typename": "MatchResultPoints"
                },
                "__typename": "MatchResult"
              }
            ],
            "timeZone": {
              "id": "169",
              "name": "America/New_York",
              "__typename": "TimeZone"
            },
            "location": {
              "id": 88174,
              "name": "National Park Pub & Grill",
              "address": {
                "id": 72204,
                "name": "National Park Pub & Grill",
                "__typename": "Address"
              },
              "__typename": "HostLocation"
            },
            "home": {
              "id": 12417130,
              "name": "Boys From The Basement",
              "number": "06802",
              "isMine": false,
              "__typename": "Team"
            },
            "away": {
              "id": 12417219,
              "name": "Eight Men Out",
              "number": "06806",
              "isMine": true,
              "__typename": "Team"
            },
            "league": {
              "id": 890,
              "isMine": true,
              "slug": "southjersey",
              "isElectronicPaymentsEnabled": false,
              "__typename": "League"
            },
            "orderItems": [],
            "division": {
              "id": 377837,
              "scheduleInEdit": false,
              "isTournament": false,
              "__typename": "Division"
            },
            "__typename": "Match"
          },
          {
            "week": 14,
            "type": "EIGHT",
            "id": 41560348,
            "isBye": false,
            "status": "COMPLETED",
            "scoresheet": null,
            "startTime": "2024-04-02T19:30:00-04:00",
            "isMine": true,
            "isPaid": false,
            "isScored": true,
            "isFinalized": true,
            "isPlayoff": false,
            "description": "",
            "tableNumber": null,
            "results": [
              {
                "homeAway": "HOME",
                "points": {
                  "total": 13,
                  "__typename": "MatchResultPoints"
                },
                "__typename": "MatchResult"
              },
              {
                "homeAway": "AWAY",
                "points": {
                  "total": 8,
                  "__typename": "MatchResultPoints"
                },
                "__typename": "MatchResult"
              }
            ],
            "timeZone": {
              "id": "169",
              "name": "America/New_York",
              "__typename": "TimeZone"
            },
            "location": {
              "id": 90042,
              "name": "Wilson's Pub",
              "address": {
                "id": 40206,
                "name": "Wilson's Pub",
                "__typename": "Address"
              },
              "__typename": "HostLocation"
            },
            "home": {
              "id": 12417219,
              "name": "Eight Men Out",
              "number": "06806",
              "isMine": true,
              "__typename": "Team"
            },
            "away": {
              "id": 12417150,
              "name": "Better Safe Than Sorry",
              "number": "06814",
              "isMine": false,
              "__typename": "Team"
            },
            "league": {
              "id": 890,
              "isMine": true,
              "slug": "southjersey",
              "isElectronicPaymentsEnabled": false,
              "__typename": "League"
            },
            "orderItems": [],
            "division": {
              "id": 377837,
              "scheduleInEdit": false,
              "isTournament": false,
              "__typename": "Division"
            },
            "__typename": "Match"
          },
          {
            "week": 15,
            "type": "EIGHT",
            "id": 41560356,
            "isBye": false,
            "status": "COMPLETED",
            "scoresheet": null,
            "startTime": "2024-04-09T19:30:00-04:00",
            "isMine": true,
            "isPaid": false,
            "isScored": true,
            "isFinalized": true,
            "isPlayoff": false,
            "description": "",
            "tableNumber": null,
            "results": [
              {
                "homeAway": "HOME",
                "points": {
                  "total": 9,
                  "__typename": "MatchResultPoints"
                },
                "__typename": "MatchResult"
              },
              {
                "homeAway": "AWAY",
                "points": {
                  "total": 11,
                  "__typename": "MatchResultPoints"
                },
                "__typename": "MatchResult"
              }
            ],
            "timeZone": {
              "id": "169",
              "name": "America/New_York",
              "__typename": "TimeZone"
            },
            "location": {
              "id": 113653,
              "name": "Spread Eagle Tavern",
              "address": {
                "id": 75396,
                "name": "Spread Eagle Tavern",
                "__typename": "Address"
              },
              "__typename": "HostLocation"
            },
            "home": {
              "id": 12417082,
              "name": "F.O.C.U.S.",
              "number": "06810",
              "isMine": false,
              "__typename": "Team"
            },
            "away": {
              "id": 12417219,
              "name": "Eight Men Out",
              "number": "06806",
              "isMine": true,
              "__typename": "Team"
            },
            "league": {
              "id": 890,
              "isMine": true,
              "slug": "southjersey",
              "isElectronicPaymentsEnabled": false,
              "__typename": "League"
            },
            "orderItems": [],
            "division": {
              "id": 377837,
              "scheduleInEdit": false,
              "isTournament": false,
              "__typename": "Division"
            },
            "__typename": "Match"
          },
          {
            "week": 16,
            "type": "EIGHT",
            "id": 41560361,
            "isBye": false,
            "status": "COMPLETED",
            "scoresheet": null,
            "startTime": "2024-04-16T19:30:00-04:00",
            "isMine": true,
            "isPaid": false,
            "isScored": true,
            "isFinalized": true,
            "isPlayoff": false,
            "description": "",
            "tableNumber": null,
            "results": [
              {
                "homeAway": "HOME",
                "points": {
                  "total": 6,
                  "__typename": "MatchResultPoints"
                },
                "__typename": "MatchResult"
              },
              {
                "homeAway": "AWAY",
                "points": {
                  "total": 17,
                  "__typename": "MatchResultPoints"
                },
                "__typename": "MatchResult"
              }
            ],
            "timeZone": {
              "id": "169",
              "name": "America/New_York",
              "__typename": "TimeZone"
            },
            "location": {
              "id": 90042,
              "name": "Wilson's Pub",
              "address": {
                "id": 40206,
                "name": "Wilson's Pub",
                "__typename": "Address"
              },
              "__typename": "HostLocation"
            },
            "home": {
              "id": 12417219,
              "name": "Eight Men Out",
              "number": "06806",
              "isMine": true,
              "__typename": "Team"
            },
            "away": {
              "id": 12416786,
              "name": "Lights Out",
              "number": "06805",
              "isMine": false,
              "__typename": "Team"
            },
            "league": {
              "id": 890,
              "isMine": true,
              "slug": "southjersey",
              "isElectronicPaymentsEnabled": false,
              "__typename": "League"
            },
            "orderItems": [],
            "division": {
              "id": 377837,
              "scheduleInEdit": false,
              "isTournament": false,
              "__typename": "Division"
            },
            "__typename": "Match"
          },
          {
            "week": 17,
            "type": "EIGHT",
            "id": 42524185,
            "isBye": false,
            "status": "COMPLETED",
            "scoresheet": null,
            "startTime": "2024-04-23T19:30:00-04:00",
            "isMine": true,
            "isPaid": false,
            "isScored": true,
            "isFinalized": true,
            "isPlayoff": false,
            "description": "",
            "tableNumber": null,
            "results": [
              {
                "homeAway": "HOME",
                "points": {
                  "total": 13,
                  "__typename": "MatchResultPoints"
                },
                "__typename": "MatchResult"
              },
              {
                "homeAway": "AWAY",
                "points": {
                  "total": 8,
                  "__typename": "MatchResultPoints"
                },
                "__typename": "MatchResult"
              }
            ],
            "timeZone": {
              "id": "169",
              "name": "America/New_York",
              "__typename": "TimeZone"
            },
            "location": {
              "id": 90042,
              "name": "Wilson's Pub",
              "address": {
                "id": 40206,
                "name": "Wilson's Pub",
                "__typename": "Address"
              },
              "__typename": "HostLocation"
            },
            "home": {
              "id": 12417219,
              "name": "Eight Men Out",
              "number": "06806",
              "isMine": true,
              "__typename": "Team"
            },
            "away": {
              "id": 12416939,
              "name": "8 Balls for Sale",
              "number": "06804",
              "isMine": false,
              "__typename": "Team"
            },
            "league": {
              "id": 890,
              "isMine": true,
              "slug": "southjersey",
              "isElectronicPaymentsEnabled": false,
              "__typename": "League"
            },
            "orderItems": [],
            "division": {
              "id": 377837,
              "scheduleInEdit": false,
              "isTournament": false,
              "__typename": "Division"
            },
            "__typename": "Match"
          },
          {
            "week": 18,
            "type": "EIGHT",
            "id": 42711053,
            "isBye": false,
            "status": "COMPLETED",
            "scoresheet": null,
            "startTime": "2024-04-30T19:30:00-04:00",
            "isMine": true,
            "isPaid": false,
            "isScored": true,
            "isFinalized": true,
            "isPlayoff": true,
            "description": "",
            "tableNumber": null,
            "results": [
              {
                "homeAway": "HOME",
                "points": {
                  "total": 10,
                  "__typename": "MatchResultPoints"
                },
                "__typename": "MatchResult"
              },
              {
                "homeAway": "AWAY",
                "points": {
                  "total": 10,
                  "__typename": "MatchResultPoints"
                },
                "__typename": "MatchResult"
              }
            ],
            "timeZone": {
              "id": "169",
              "name": "America/New_York",
              "__typename": "TimeZone"
            },
            "location": {
              "id": 90042,
              "name": "Wilson's Pub",
              "address": {
                "id": 40206,
                "name": "Wilson's Pub",
                "__typename": "Address"
              },
              "__typename": "HostLocation"
            },
            "home": {
              "id": 12417219,
              "name": "Eight Men Out",
              "number": "06806",
              "isMine": true,
              "__typename": "Team"
            },
            "away": {
              "id": 12417425,
              "name": "Break 8 Away",
              "number": "06811",
              "isMine": false,
              "__typename": "Team"
            },
            "league": {
              "id": 890,
              "isMine": true,
              "slug": "southjersey",
              "isElectronicPaymentsEnabled": false,
              "__typename": "League"
            },
            "orderItems": [],
            "division": {
              "id": 377837,
              "scheduleInEdit": false,
              "isTournament": false,
              "__typename": "Division"
            },
            "__typename": "Match"
          }
        ],
        "__typename": "Team"
      }
    }
  }
}